CHANGELOG.txt
LICENCE.txt
MANIFEST.in
README.txt
setup.py
gbprocess/__init__.py
gbprocess.egg-info/PKG-INFO
gbprocess.egg-info/SOURCES.txt
gbprocess.egg-info/dependency_links.txt
gbprocess.egg-info/top_level.txt