Metadata-Version: 1.1
Name: gbprocess
Version: 0.0.1
Summary: A basic binary converter
Home-page: UNKNOWN
Author: Bibin Shajan
Author-email: bibinmoolakkara@gmail.com
License: MIT
Keywords: binary
Platform: UNKNOWN
Classifier: Development Status :: 5 - Production/Stable
Classifier: Intended Audience :: Education
Classifier: Operating System :: Microsoft :: Windows :: Windows 10
Classifier: License :: OSI Approved :: MIT License
Classifier: Programming Language :: Python :: 3
